pandoc_run_postgres.py
pandoc_run_postgres-0.1.0.dist-info/METADATA
pandoc_run_postgres-0.1.0.dist-info/WHEEL
pandoc_run_postgres-0.1.0.dist-info/entry_points.txt
pandoc_run_postgres-0.1.0.dist-info/top_level.txt
pandoc_run_postgres-0.1.0.dist-info/RECORD
